matlabreport/__init__.py
matlabreport/makereport.py
matlabreport/openreport.py
matlabreport/publishmfile.py
matlabreport/scripts/__init__.py
matlabreport/scripts/autoreport.py
matlabreport/scripts/matlabreport.py
matlabreport/scripts/mintify.py
matlabreport-0.6.0.dist-info/METADATA
matlabreport-0.6.0.dist-info/RECORD
matlabreport-0.6.0.dist-info/WHEEL
matlabreport-0.6.0.dist-info/entry_points.txt
matlabreport-0.6.0.dist-info/top_level.txt
tests/__init__.py
tests/test_makereport.py
