Metadata-Version: 2.1
Name: matlabreport
Version: 0.6.0
Summary: Make and publish MATLAB reports.
Home-page: https://github.com/ahoetker/matlabreport
Author: Andrew Hoetker
Author-email: ahoetker@me.com
License: UNKNOWN
Platform: UNKNOWN
Requires-Dist: Click
